json2netns/__init__.py
json2netns/config.py
json2netns/consts.py
json2netns/interfaces.py
json2netns/main.py
json2netns/netns.py
json2netns/route.py
json2netns/sample.json
json2netns/tests/base.py
json2netns/tests/interfaces.py
json2netns/tests/netns.py
json2netns/tests/route.py
json2netns-2021.9.20.dist-info/LICENSE
json2netns-2021.9.20.dist-info/METADATA
json2netns-2021.9.20.dist-info/WHEEL
json2netns-2021.9.20.dist-info/entry_points.txt
json2netns-2021.9.20.dist-info/top_level.txt
json2netns-2021.9.20.dist-info/RECORD
