Metadata-Version: 2.1
Name: json2netns
Version: 2021.9.20
Summary: JSON parsing Linux Network Namespace (netns) topology builder.
Home-page: https://github.com/cooperlees/json2netns
Author: Cooper Ry Lees
Author-email: me@cooperlees.com
License: BSD
Keywords: json linux netns network namespace
Platform: UNKNOWN
Classifier: Development Status :: 4 - Beta
Classifier: Environment :: Console
Classifier: Intended Audience :: Developers
Classifier: License :: OSI Approved :: BSD License
Classifier: Programming Language :: Python
Classifier: Programming Language :: Python :: 3.8
Classifier: Programming Language :: Python :: 3.9
Classifier: Programming Language :: Python :: 3 :: Only
Requires-Python: >=3.8.0
License-File: LICENSE
